Metadata-Version: 2.1
Name: example_package_PERRIN_Liam
Version: 0.0.3
Summary: Test du deploiement
Project-URL: Homepage, https://github.com/Sletty4/M1-2022-git-workflow-PERRIN-Liam
Project-URL: Bug Tracker, https://github.com/Sletty4/M1-2022-git-workflow-PERRIN-Liam/issues
Author-email: PERRIN_Liam <liam.perrin@isen.yncrea.fr>
License-File: LICENSE
Classifier: License :: OSI Approved :: MIT License
Classifier: Operating System :: OS Independent
Classifier: Programming Language :: Python :: 3
Requires-Python: >=3.7
